capov/__init__.py
capov/__main__.py
capov/example.py
capov/fixers.py
capov/tests/__init__.py
capov/tests/__main__.py
capov/tests/test_cli_full.py
capov/tests/test_cli_params.py
capov/tests/test_module_usage.py
capov/tests/faulty_scripts/__init__.py
capov/tests/faulty_scripts/faulty_extra_closing_paren.py
capov/tests/faulty_scripts/faulty_group_imports.py
capov/tests/faulty_scripts/faulty_imports_inside_func.py
capov/tests/faulty_scripts/faulty_inline_comments.py
capov/tests/faulty_scripts/faulty_nested_brackets.py
capov-0.1.6.dist-info/METADATA
capov-0.1.6.dist-info/WHEEL
capov-0.1.6.dist-info/entry_points.txt
capov-0.1.6.dist-info/top_level.txt
capov-0.1.6.dist-info/RECORD
