Metadata-Version: 2.4
Name: capov
Version: 0.1.6
Summary: Captain Obvious: Corrects all the obvious errors in a Python-script.
Author: Hans-Peter Radtke
License: MIT
Requires-Python: >=3.11
Requires-Dist: autoimport<2.0.0,>=1.0.0
Provides-Extra: test
Requires-Dist: pytest; extra == "test"
